Workbook

Sheet Raw Data
A1: Tata Motors — Consolidated Financial Data
A3: Metric | B3: FY2024 | C3: FY2025
A4: Revenue | B4: 434016 | C4: 439695
A5: EBITDA | B5: 61196 | C5: 57649
A6: Profit After Tax | B6: 31807 | C6: 28149
A7: EBIT | B7: 34721 | C7: 34735.61
A8: ROCE | B8: 0.187 | C8: 0.176
A9: Auto Free Cash Flow | B9: 26925 | C9: 22348

Sheet Working Capital
A1: Tata Motors — Working Capital Data
A3: Metric | B3: FY2023 | C3: FY2024 | D3: FY2025
A4: Trade Receivables | B4: 15737.97 | C4: 16951.81 | D4: 13248
A5: Inventory | B5: 40755.39 | C5: 47788.29 | D5: 47269
A6: Trade Payables | B6: 72055.77 | C6: 88042.95 | D6: 93626
A7: Raw Material Consumed | B7: 226469.64 | C7: 272755.7 | D7: 271786
A8: Revenue | C8: 434016 | D8: 439695

Sheet KPI Calculations
A1: Tata — KPI Analysis
A3: KPI | B3: FY2024 | C3: FY2025 | D3: Change
A4: Revenue Growth | C4: =(('Raw Data'!C4-'Raw Data'!B4)/'Raw Data'!B4) -> 0.013084771
A5: EBITDA Margin | B5: ='Raw Data'!B5/'Raw Data'!B4 -> 0.14099941 | C5: ='Raw Data'!C5/'Raw Data'!C4 -> 0.13111134 | D5: =(C5-B5)*100 -> -0.98880716
A6: PAT Margin | B6: ='Raw Data'!B6/'Raw Data'!B4 -> 0.073285317 | C6: ='Raw Data'!C6/'Raw Data'!C4 -> 0.064019377 | D6: =(C6-B6)*100 -> -0.92659396
A7: ROCE | B7: ='Raw Data'!B8 -> 0.187 | C7: ='Raw Data'!C8 -> 0.176 | D7: =(C7-B7)*100 -> -1.1
A8: DSO | B8: =AVERAGE('Working Capital'!B4:C4)/'Working Capital'!C8*365 -> 13.745772 | C8: =AVERAGE('Working Capital'!C4:D4)/'Working Capital'!D8*365 -> 12.534746 | D8: =C8-B8 -> -1.2110253
A9: DIO | B9: =AVERAGE('Working Capital'!B5:C5)/'Working Capital'!C7*365 -> 59.244304 | C9: =AVERAGE('Working Capital'!C5:D5)/'Working Capital'!D7*365 -> 63.829467 | D9: =C9-B9 -> 4.5851627
A10: DPO | B10: =AVERAGE('Working Capital'!B6:C6)/'Working Capital'!C7*365 -> 107.12156 | C10: =AVERAGE('Working Capital'!C6:D6)/'Working Capital'!D7*365 -> 121.98783 | D10: =C10-B10 -> 14.866265
A11: CCC | B11: =B9+B8-B10 -> -34.131485 | C11: =C9+C8-C10 -> -45.623613 | D11: =C11-B11 -> -11.492128

Sheet Dashboard
A1: Tata Motors — Executive KPI Dashboard
A2: Consolidated | FY2024 vs FY2025
A4: Revenue Growth | C4: EBITDA Margin | E4: PAT Margin | G4: ROCE
A5: ='KPI Calculations'!C4 -> 0.013084771 | C5: ='KPI Calculations'!C5 -> 0.13111134 | E5: ='KPI Calculations'!C6 -> 0.064019377 | G5: ='KPI Calculations'!C7 -> 0.176
A8: DSO | C8: DIO | E8: DPO | G8: CCC
A9: ='KPI Calculations'!C8 -> 12.534746 | C9: ='KPI Calculations'!C9 -> 63.829467 | E9: ='KPI Calculations'!C10 -> 121.98783 | G9: ='KPI Calculations'!C11 -> -45.623613

Sheet Insights
A1: Tata Motors — Management Insights | D1: Competitive Snapshot — FY2025
A2: Consolidated | FY2024 vs FY2025
A4: Area | B4: Analyst Observation | D4: Metric | E4: Tata Motors | F4: Mahindra & Mahindra | G4: Maruti Suzuki
A5: Revenue | B5: Revenue increased by 1.31% in FY2025, indicating modest top-line growth compared with FY2024. | D5: Revenue / Income from Operations (₹ Cr) | E5: 439695 | F5: 159211 | G5: 145115
A6: Profitability | B6: Profitability weakened in FY2025. EBITDA margin declined from 14.10% to 13.11%, while net profit margin declined from 7.33% to 6.40%, indicating pressure on operating and bottom-line profitability. | D6: PAT (₹ Cr) | E6: 28149 | F6: 12929 | G6: 13955
A7: Working Capital | B7: DSO improved from 13.75 to 12.53 days, while DIO increased from 59.24 to 63.83 days. DPO increased from 107.12 to 121.99 days, resulting in a more negative CCC of -45.62 days. | D7: Revenue Growth | E7: 0.013 | F7: 0.14 | G7: 0.075
A8: Capital Efficiency | B8: ROCE declined from 18.70% to 17.60%, indicating a modest deterioration in the efficiency of capital employed. | D8: Key Position | E8: PV + CV + JLR | F8: SUV + LCV + Farm | G8: Passenger Vehicles
A9: Overall Assessment | B9: Overall, FY2025 showed modest revenue growth but weaker profitability and ROCE. Working-capital indicators were mixed, with improved collections and higher supplier payment days partly offsetting the increase in inventory days. Management should focus on margin protection, inventory efficiency and sustaining strong cash conversion.
D10: Key Takeaways
A12: Tata Motors — Company & Industry Analysis
D13: Finding | E13: Implication
A14: Area | B14: Analysis | D14: Tata Motors has the largest revenue base | E14: Strong scale and diversified operations
A15: Business Model | B15: Tata Motors operates across passenger vehicles, commercial vehicles and Jaguar Land Rover, with exposure to both domestic and international automotive markets. Its business is therefore influenced by vehicle demand, product mix, pricing, commodity costs, foreign exchange and financing conditions. | D15: M&M has faster revenue growth | E15: Stronger recent growth momentum
A16: Key Revenue Drivers | B16: Key revenue drivers include vehicle volumes, pricing, product mix, premium vehicle demand, commercial vehicle demand, international sales and new product launches. | D16: Maruti has strong passenger-vehicle positioning | E16: Strong competitive position in India's PV market
A17: Industry Trends | B17: The Indian automotive market remained resilient in FY2024-25, with passenger vehicles reaching record sales while commercial vehicles experienced a slight decline. EV adoption, financing costs, consumer affordability and regulatory support remain important industry factors. | D17: Tata Motors' margins declined | E17: Margin protection should remain a management priority
A18: Growth Opportunities | B18: Growth opportunities include SUV and premium-vehicle demand, EV adoption, commercial-vehicle replacement demand, exports and new product launches.
A19: Key Risks | B19: Key risks include commodity-price volatility, intense competition, foreign-exchange movements, changes in interest rates, supply-chain disruptions and the pace and cost of electrification.
A20: Competitive Landscape | B20: Tata Motors competes across multiple automotive segments, with major Indian competitors including Maruti Suzuki and Mahindra & Mahindra in passenger vehicles and Ashok Leyland in commercial vehicles. Competitive intensity is particularly important in SUVs, EVs and commercial vehicles.
